setup.py
bin/slask
slask/__init__.py
slask/slask.py
slask.egg-info/PKG-INFO
slask.egg-info/SOURCES.txt
slask.egg-info/dependency_links.txt
slask.egg-info/not-zip-safe
slask.egg-info/requires.txt
slask.egg-info/top_level.txt