Metadata-Version: 1.0
Name: slask
Version: 0.1
Summary: A Flask app to republish to Slack
Home-page: http://github.com/benkershner/slask
Author: Ben Kershner
Author-email: benkershner@gmail.com
License: MIT
Platform: UNKNOWN
